{
  "hash": "8e04f320",
  "configHash": "5c12662d",
  "lockfileHash": "8370162b",
  "browserHash": "0a5fb221",
  "optimized": {
    "vue": {
      "src": "../../../node_modules/vue/dist/vue.runtime.esm-bundler.js",
      "file": "vue.js",
      "fileHash": "3c0d2fa1",
      "needsInterop": false
    },
    "vitepress > @vue/devtools-api": {
      "src": "../../../node_modules/@vue/devtools-api/dist/index.js",
      "file": "vitepress___@vue_devtools-api.js",
      "fileHash": "c6cfcd54",
      "needsInterop": false
    },
    "vitepress > @vueuse/core": {
      "src": "../../../node_modules/@vueuse/core/index.mjs",
      "file": "vitepress___@vueuse_core.js",
      "fileHash": "074f53d9",
      "needsInterop": false
    }
  },
  "chunks": {
    "chunk-Z6B2QTD3": {
      "file": "chunk-Z6B2QTD3.js"
    }
  }
}